hand_mouse/README.md
hand_mouse/__init__.py
hand_mouse/cursor.py
hand_mouse/eye_tracker.py
hand_mouse/keyboard.py
hand_mouse/tracker.py
hand_mouse/utils.py
hand_mouse/docs/Course.md
hand_mouse/docs/Integration.md
hand_mouse/tests/test_cursor.py
hand_mouse/tests/test_dwell.py
hand_mouse/tests/test_eye_blink.py
hand_mouse/tests/test_hand_clap.py
hand_mouse/tests/test_integration_imports.py
hand_mouse/tests/test_keyboard.py
hand_mouse/tests/test_scroll.py
hand_mouse/tests/test_utils.py
hand_mouse-0.1.0.dist-info/licenses/LICENSE
hand_mouse-0.1.0.dist-info/METADATA
hand_mouse-0.1.0.dist-info/WHEEL
hand_mouse-0.1.0.dist-info/top_level.txt
hand_mouse-0.1.0.dist-info/RECORD
